[[1.454183,{"lines":{"0":[["../bundle/ctrlp                                                                                                                                                                                                                    ",{}]],"1":[["                                                                                                                                                                                                                                   ",{}]],"2":[["                                                                                                                                                                                                                                   ",{}]],"3":[["                                                                                                                                                                                                                                   ",{}]],"4":[["                                                                                                                                                                                                                                   ",{}]],"5":[["                                                                                                                                                                                                                                   ",{}]],"6":[["                                                                                                                                                                                                                                   ",{}]],"7":[["                                                                                                                                                                                                                                   ",{}]],"8":[["                                                                                                                                                                                                                                   ",{}]],"9":[["                                                                                                                                                                                                                                   ",{}]],"10":[["                                                                                                                                                                                                                                   ",{}]],"11":[["                                                                                                                                                                                                                                   ",{}]],"12":[["                                                                                                                                                                                                                                   ",{}]],"13":[["                                                                                                                                                                                                                                   ",{}]],"14":[["                                                                                                                                                                                                                                   ",{}]],"15":[["                                                                                                                                                                                                                                   ",{}]],"16":[["                                                                                                                                                                                                                                   ",{}]],"17":[["                                                                                                                                                                                                                                   ",{}]],"18":[["                                                                                                                                                                                                                                   ",{}]],"19":[["                                                                                                                                                                                                                                   ",{}]],"20":[["                                                                                                                                                                                                                                   ",{}]],"21":[["                                                                                                                                                                                                                                   ",{}]],"22":[["                                                                                                                                                                                                                                   ",{}]],"23":[["                                                                                                                                                                                                                                   ",{}]],"24":[["                                                                                                                                                                                                                                   ",{}]],"25":[["                                                                                                                                                                                                                                   ",{}]],"26":[["                                                                                                                                                                                                                                   ",{}]],"27":[["                                                                                                                                                                                                                                   ",{}]],"28":[["                                                                                                                                                                                                                                   ",{}]],"29":[["                                                                                                                                                                                                                                   ",{}]],"30":[["                                                                                                                                                                                                                                   ",{}]],"31":[["                                                                                                                                                                                                                                   ",{}]],"32":[["                                                                                                                                                                                                                                   ",{}]],"33":[["                                                                                                                                                                                                                                   ",{}]],"34":[["                                                                                                                                                                                                                                   ",{}]],"35":[["                                                                                                                                                                                                                                   ",{}]],"36":[["                                                                                                                                                                                                                                   ",{}]],"37":[["                                                                                                                                                                                                                                   ",{}]],"38":[["                                                                                                                                                                                                                                   ",{}]],"39":[["                                                                                                                                                                                                                                   ",{}]],"40":[["                                                                                                                                                                                                                                   ",{}]],"41":[["                                                                                                                                                                                                                                   ",{}]],"42":[["                                                                                                                                                                                                                                   ",{}]],"43":[["                                                                                                                                                                                                                                   ",{}]],"44":[["                                                                                                                                                                                                                                   ",{}]],"45":[["                                                                                                                                                                                                                                   ",{}]],"46":[["                                                                                                                                                                                                                                   ",{}]],"47":[["                                                                                                                                                                                                                                   ",{}]],"48":[["                                                                                                                                                                                                                                   ",{}]],"49":[["                                                                                                                                                                                                                                   ",{}]],"50":[["                                                                                                                                                                                                                                   ",{}]],"51":[["                                                                                                                                                                                                                                   ",{}]],"52":[["                                                                                                                                                                                                                                   ",{}]],"53":[["                                                                                                                                                                                                                                   ",{}]],"54":[["                                                                                                                                                                                                                                   ",{}]],"55":[["                                                                                                                                                                                                                                   ",{}]],"56":[["                                                                                                                                                                                                                                   ",{}]]},"cursor":{"x":15,"y":0,"visible":true}}],[0.394887,{"lines":{"0":[["tadeu",{"fg":105}],[" on ",{}],["~/d/v/b/ctrlp",{"fg":34}],[" ±master>",{"fg":246}],["                                                                                                                                                                                                    ",{}]]},"cursor":{"x":32}}],[0.000557,{}],[0.389659,{}],[0.313916,{"lines":{"0":[["tadeu",{"fg":105}],[" on ",{}],["~/d/v/b/ctrlp",{"fg":34}],[" ±master>",{"fg":246}],[" ",{}],["l",{"fg":1,"bold":true}],["                                                                                                                                                                                                  ",{}]]},"cursor":{"x":33}}],[0.064208,{"lines":{"0":[["tadeu",{"fg":105}],[" on ",{}],["~/d/v/b/ctrlp",{"fg":34}],[" ±master>",{"fg":246}],[" ",{}],["ls",{"fg":2}],["                                                                                                                                                                                                 ",{}]]},"cursor":{"x":34}}],[0.108519,{}],[0.394309,{}],[0.007967,{"lines":{"1":[["ls",{}],["autoload",{"fg":6,"bold":true}],["  ",{}],["doc",{"fg":6,"bold":true}],["       ",{}],["plugin",{"fg":6,"bold":true}],["    readme.md                                                                                                                                                                                          ",{}]],"2":[["../bundle/ctrlp                                                                                                                                                                                                                    ",{}]]},"cursor":{"x":15,"y":2}}],[0.067787,{"lines":{"2":[["../bundle/ctrlpcd                                                                                                                                                                                                                  ",{}]]},"cursor":{"x":17}}],[0.056008,{"cursor":{"x":18}}],[0.087994,{"lines":{"2":[["../bundle/ctrlpcd .                                                                                                                                                                                                                ",{}]]},"cursor":{"x":19}}],[0.127937,{"lines":{"2":[["../bundle/ctrlpcd ..                                                                                                                                                                                                               ",{}]]},"cursor":{"x":20}}],[0.03046,{"lines":{"2":[["tadeu",{"fg":105}],[" on ",{}],["~/d/v/b/ctrlp",{"fg":34}],[" ±master>",{"fg":246}],["                                                                                                                                                                                                    ",{}]]},"cursor":{"x":32}}],[0.000162,{}],[0.360982,{}],[0.001693,{"lines":{"2":[["tadeu",{"fg":105}],[" on ",{}],["~/d/v/b/ctrlp",{"fg":34}],[" ±master>",{"fg":246}],[" cd ..                                                                                                                                                                                              ",{}]]},"cursor":{"x":37}}],[0.373944,{}],[0.000693,{"lines":{"3":[["cd                                                                                                                                                                                                                                 ",{}]]},"cursor":{"x":2,"y":3}}],[0.038654,{"lines":{"3":[["cd",{}],["%",{"bold":true}],["                                                                                                                                                                                                                                ",{}]],"4":[["..es/vim/bundle                                                                                                                                                                                                                    ",{}]]},"cursor":{"x":15,"y":4}}],[0.48135,{"lines":{"4":[["..es/vim/bundlels                                                                                                                                                                                                                  ",{}]],"5":[["c                                                                                                                                                                                                                                  ",{}]]},"cursor":{"x":1,"y":5}}],[0.01251,{"lines":{"5":[["tadeu",{"fg":105}],[" on ",{}],["~/d/v/bundle",{"fg":34}],[" ±master>",{"fg":246}],["                                                                                                                                                                                                     ",{}]]},"cursor":{"x":31}}],[0.059476,{"lines":{"5":[["tadeu",{"fg":105}],[" on ",{}],["~/d/v/bundle",{"fg":34}],[" ±master>",{"fg":246}],[" d                                                                                                                                                                                                   ",{}]]},"cursor":{"x":32}}],[0.064126,{"cursor":{"x":33}}],[0.087826,{"lines":{"5":[["tadeu",{"fg":105}],[" on ",{}],["~/d/v/bundle",{"fg":34}],[" ±master>",{"fg":246}],[" d .                                                                                                                                                                                                 ",{}]]},"cursor":{"x":34}}],[0.103986,{"lines":{"5":[["tadeu",{"fg":105}],[" on ",{}],["~/d/v/bundle",{"fg":34}],[" ±master>",{"fg":246}],[" d ..                                                                                                                                                                                                ",{}]]},"cursor":{"x":35}}],[0.165888,{"lines":{"5":[["tadeu",{"fg":105}],[" on ",{}],["~/d/v/bundle",{"fg":34}],[" ±master>",{"fg":246}],["                                                                                                                                                                                                     ",{}]]},"cursor":{"x":31}}],[0.010281,{"lines":{"5":[["tadeu",{"fg":105}],[" on ",{}],["~/d/v/bundle",{"fg":34}],[" ±master>",{"fg":246}],[" ",{}],["ls",{"fg":2}],["                                                                                                                                                                                                  ",{}]]},"cursor":{"x":0,"y":6}}],[0.151822,{"lines":{"6":[["l                                                                                                                                                                                                                                  ",{}]]},"cursor":{"x":1}}],[0.136124,{"lines":{"6":[["ls                                                                                                                                                                                                                                 ",{}]]},"cursor":{"x":2}}],[0.104088,{"cursor":{"x":0,"y":7}}],[0.08588700000000001,{"lines":{"7":[["tadeu",{"fg":105}],[" on ",{}],["~/d/v/bundle",{"fg":34}],[" ±master>",{"fg":246}],[" ",{}],["ls",{"fg":2}],["                                                                                                                                                                                                  ",{}]]},"cursor":{"x":33}}],[0.003978000000000001,{"lines":{"8":[["ls",{}],["clang_complete",{"fg":6,"bold":true}],["             ",{}],["ctrlp",{"fg":6,"bold":true}],["                      ",{}],["syntastic",{"fg":6,"bold":true}],["                  ",{}],["vim-coffee-script",{"fg":6,"bold":true}],["          ",{}],["vim-ios",{"fg":6,"bold":true}],["                    ",{}],["vim-objc",{"fg":6,"bold":true}],["                                                                                  ",{}]],"9":[["clang_complete-getopts-ios",{"fg":6,"bold":true}],[" ",{}],["kiwi.vim",{"fg":6,"bold":true}],["                   ",{}],["tabular",{"fg":6,"bold":true}],["                    ",{}],["vim-fugitive",{"fg":6,"bold":true}],["               ",{}],["vim-javascript",{"fg":6,"bold":true}],["             ",{}],["vimux",{"fg":6,"bold":true}],["                                                                                       ",{}]],"10":[["cocoa.vim",{"fg":6,"bold":true}],["                  ",{}],["nerdcommenter",{"fg":6,"bold":true}],["              ",{}],["ultisnips",{"fg":6,"bold":true}],["                  ",{}],["vim-haml",{"fg":6,"bold":true}],["                   ",{}],["vim-jquery",{"fg":6,"bold":true}],["                                                                                                             ",{}]],"11":[["..es/vim/bundle                                                                                                                                                                                                                    ",{}]]},"cursor":{"x":15,"y":11}}],[0.270104,{"lines":{"11":[["..es/vim/bundlec                                                                                                                                                                                                                   ",{}]]},"cursor":{"x":16}}],[0.055807,{"lines":{"11":[["..es/vim/bundlecd                                                                                                                                                                                                                  ",{}]]},"cursor":{"x":17}}],[0.08802599999999999,{"cursor":{"x":18}}],[0.073547,{"lines":{"11":[["tadeu",{"fg":105}],[" on ",{}],["~/d/v/bundle",{"fg":34}],[" ±master>",{"fg":246}],["                                                                                                                                                                                                     ",{}]]},"cursor":{"x":31}}],[0.014435,{"lines":{"11":[["tadeu",{"fg":105}],[" on ",{}],["~/d/v/bundle",{"fg":34}],[" ±master>",{"fg":246}],[" .                                                                                                                                                                                                   ",{}]]},"cursor":{"x":32}}],[0.128188,{"lines":{"11":[["tadeu",{"fg":105}],[" on ",{}],["~/d/v/bundle",{"fg":34}],[" ±master>",{"fg":246}],[" ..                                                                                                                                                                                                  ",{}]]},"cursor":{"x":33}}],[0.13594,{"cursor":{"x":0,"y":12}}],[0.135837,{"lines":{"12":[["l                                                                                                                                                                                                                                  ",{}]]},"cursor":{"x":1}}],[0.062764,{"lines":{"12":[["tadeu",{"fg":105}],[" on ",{}],["~/d/v/bundle",{"fg":34}],[" ±master>",{"fg":246}],["                                                                                                                                                                                                     ",{}]]},"cursor":{"x":31}}],[0.001528,{"lines":{"12":[["tadeu",{"fg":105}],[" on ",{}],["~/d/v/bundle",{"fg":34}],[" ±master>",{"fg":246}],[" cd ..                                                                                                                                                                                               ",{}]]},"cursor":{"x":36}}],[0.042311,{"lines":{"12":[["tadeu",{"fg":105}],[" on ",{}],["~/d/v/bundle",{"fg":34}],[" ±master>",{"fg":246}],[" cd ..s                                                                                                                                                                                              ",{}]]},"cursor":{"x":37}}],[0.045762,{"cursor":{"x":0,"y":13}}],[0.3049,{"lines":{"13":[["c                                                                                                                                                                                                                                  ",{}]]},"cursor":{"x":1}}],[0.07087599999999999,{"lines":{"13":[["cd                                                                                                                                                                                                                                 ",{}]]},"cursor":{"x":2}}],[0.0713,{"lines":{"13":[["tadeu",{"fg":105}],[" on ",{}],["~/d/v/bundle",{"fg":34}],[" ±master>",{"fg":246}],[" cd ..                                                                                                                                                                                               ",{}]]},"cursor":{"x":36}}],[0.016642,{"lines":{"14":[["cdcd                                                                                                                                                                                                                               ",{}]]},"cursor":{"x":5,"y":14}}],[0.020574,{"lines":{"14":[["cdcd ",{}],["%",{"bold":true}],["                                                                                                                                                                                                                             ",{}]],"15":[["~/dotfiles/vim                                                                                                                                                                                                                     ",{}]]},"cursor":{"x":14,"y":15}}],[0.05934,{"lines":{"15":[["~/dotfiles/vim.                                                                                                                                                                                                                    ",{}]]},"cursor":{"x":15}}],[0.119978,{"lines":{"15":[["~/dotfiles/vim..                                                                                                                                                                                                                   ",{}]]},"cursor":{"x":16}}],[0.224073,{"cursor":{"x":0,"y":16}}],[0.079998,{"lines":{"16":[["tadeu",{"fg":105}],[" on ",{}],["~/d/vim",{"fg":34}],[" ±master>",{"fg":246}],["                                                                                                                                                                                                          ",{}]]},"cursor":{"x":26}}],[0.000159,{}],[0.071921,{"lines":{"16":[["tadeu",{"fg":105}],[" on ",{}],["~/d/vim",{"fg":34}],[" ±master>",{"fg":246}],[" l                                                                                                                                                                                                        ",{}]]},"cursor":{"x":27}}],[0.04804,{"lines":{"16":[["tadeu",{"fg":105}],[" on ",{}],["~/d/vim",{"fg":34}],[" ±master>",{"fg":246}],[" ls                                                                                                                                                                                                       ",{}]]},"cursor":{"x":28}}],[0.364546,{"lines":{"16":[["tadeu",{"fg":105}],[" on ",{}],["~/d/vim",{"fg":34}],[" ±master>",{"fg":246}],["                                                                                                                                                                                                          ",{}]]},"cursor":{"x":26}}],[0.0006190000000000001,{"lines":{"16":[["tadeu",{"fg":105}],[" on ",{}],["~/d/vim",{"fg":34}],[" ±master>",{"fg":246}],[" ls                                                                                                                                                                                                       ",{}]]},"cursor":{"x":28}}],[0.130706,{"cursor":{"x":0,"y":17}}],[0.351397,{"lines":{"17":[["tadeu",{"fg":105}],[" on ",{}],["~/d/vim",{"fg":34}],[" ±master>",{"fg":246}],[" ls                                                                                                                                                                                                       ",{}]]},"cursor":{"x":28}}],[0.004066,{"lines":{"18":[["ls",{}],["autoload",{"fg":6,"bold":true}],[" ",{}],["bin",{"fg":6,"bold":true}],["      ",{}],["bundle",{"fg":6,"bold":true}],["   ",{}],["colors",{"fg":6,"bold":true}],["   ",{}],["doc",{"fg":6,"bold":true}],["      ",{}],["plugin",{"fg":6,"bold":true}],["   ",{}],["readlink",{"fg":5}],[" ",{}],["vim",{"fg":5}],["                                                                                                                                                               ",{}]],"19":[["~/dotfiles/vim                                                                                                                                                                                                                     ",{}]]},"cursor":{"x":14,"y":19}}],[0.472783,{"lines":{"19":[["tadeu",{"fg":105}],[" on ",{}],["~/d/vim",{"fg":34}],[" ±master>",{"fg":246}],["                                                                                                                                                                                                          ",{}]]},"cursor":{"x":26}}],[0.000169,{}],[0.4738,{}],[0.001515,{"lines":{"19":[["tadeu",{"fg":105}],[" on ",{}],["~/d/vim",{"fg":34}],[" ±master>",{"fg":246}],[" cd ..                                                                                                                                                                                                    ",{}]]},"cursor":{"x":31}}],[0.469049,{}],[0.000688,{"lines":{"20":[["cd                                                                                                                                                                                                                                 ",{}]]},"cursor":{"x":2,"y":20}}],[0.034768,{"lines":{"20":[["cd",{}],["%",{"bold":true}],["                                                                                                                                                                                                                                ",{}]],"21":[["~/dotfiles                                                                                                                                                                                                                         ",{}]]},"cursor":{"x":10,"y":21}}],[0.493217,{"lines":{"21":[["tadeu",{"fg":105}],[" on ",{}],["~/dotfiles",{"fg":34}],[" ±master>",{"fg":246}],["                                                                                                                                                                                                       ",{}]]},"cursor":{"x":29}}],[0.00014,{}],[0.480759,{}],[0.000664,{"lines":{"21":[["tadeu",{"fg":105}],[" on ",{}],["~/dotfiles",{"fg":34}],[" ±master>",{"fg":246}],[" ls                                                                                                                                                                                                    ",{}]]},"cursor":{"x":31}}],[0.478871,{}],[0.004403,{"lines":{"22":[["lsRailsCasts.dvtcolortheme                  ",{}],["dependencies.txt",{"fg":1}],["                          ",{}],["oh-my-zsh",{"fg":6,"bold":true}],["                                 vim-modules.txt                           ",{}],["zsh-syntax-highlighting",{"fg":6,"bold":true}],["                                  ",{}]],"23":[["Source+Code+Pro+Regular+for+Powerline.otf",{"fg":1}],[" ",{}],["gitconfig",{"fg":1}],["                                 ",{}],["tmux.conf",{"fg":1}],["                                 ",{}],["vimrc",{"fg":1}],["                                     ",{}],["zshrc",{"fg":1}],["                                                      ",{}]],"24":[["bin",{"fg":6,"bold":true}],["                                       ",{}],["install.sh",{"fg":1}],["                                ",{}],["vim",{"fg":6,"bold":true}],["                                       ",{}],["xvimrc",{"fg":1}],["                                                                                               ",{}]],"25":[["config",{"fg":6,"bold":true}],["                                    ",{}],["my-custom.zsh-theme",{"fg":1}],["                       ",{}],["vim-markdown-preview",{"fg":6,"bold":true}],["                      ",{}],["zsh-history-substring-search",{"fg":6,"bold":true}],["                                                                         ",{}]],"26":[["~/dotfiles                                                                                                                                                                                                                         ",{}]]},"cursor":{"x":10,"y":26}}],[0.495601,{"lines":{"26":[["tadeu",{"fg":105}],[" on ",{}],["~/dotfiles",{"fg":34}],[" ±master>",{"fg":246}],["                                                                                                                                                                                                       ",{}]]},"cursor":{"x":29}}],[0.000212,{}],[0.48871,{}],[0.001518,{"lines":{"26":[["tadeu",{"fg":105}],[" on ",{}],["~/dotfiles",{"fg":34}],[" ±master>",{"fg":246}],[" cd ..                                                                                                                                                                                                 ",{}]]},"cursor":{"x":34}}],[0.485581,{}],[0.0006630000000000001,{"lines":{"27":[["cd                                                                                                                                                                                                                                 ",{}]]},"cursor":{"x":2,"y":27}}],[0.034623,{"lines":{"27":[["cd",{}],["%",{"bold":true}],["                                                                                                                                                                                                                                ",{}]],"28":[["~                                                                                                                                                                                                                                  ",{}]]},"cursor":{"x":1,"y":28}}],[0.089993,{"lines":{"28":[["tadeu",{"fg":105}],[" on ",{}],["~",{"fg":34}],[">",{"fg":246}],["                                                                                                                                                                                                                        ",{}]]},"cursor":{"x":12}}],[0.000176,{}],[0.08706800000000001,{}],[0.002829,{"lines":{"28":[["tadeu",{"fg":105}],[" on ",{}],["~",{"fg":34}],[">",{"fg":246}],[" ",{}],["ls",{"fg":2}],["                                                                                                                                                                                                                     ",{}]]},"cursor":{"x":14}}],[0.086317,{}],[0.004247,{"lines":{"29":[["ls",{}],["Desktop",{"fg":6,"bold":true}],["   ",{}],["Documents",{"fg":6,"bold":true}],[" ",{}],["Downloads",{"fg":6,"bold":true}],[" ",{}],["Dropbox",{"fg":6,"bold":true}],["   ",{}],["Library",{"fg":6,"bold":true}],["   ",{}],["Movies",{"fg":6,"bold":true}],["    ",{}],["Music",{"fg":6,"bold":true}],["     ",{}],["Pictures",{"fg":6,"bold":true}],["  ",{}],["Public",{"fg":6,"bold":true}],["    ",{}],["dotfiles",{"fg":6,"bold":true}],["  ",{}],["www",{"fg":6,"bold":true}],["                                                                                                                          ",{}]],"30":[["~                                                                                                                                                                                                                                  ",{}]]},"cursor":{"x":1,"y":30}}],[0.089597,{"lines":{"30":[["tadeu",{"fg":105}],[" on ",{}],["~",{"fg":34}],[">",{"fg":246}],["                                                                                                                                                                                                                        ",{}]]},"cursor":{"x":12}}],[0.000191,{}],[0.089377,{}],[0.778469,{"cursor":{"x":0,"y":31}}]]